odoo/addons/purchase_requisition_multiple_vendor/README.rst
odoo/addons/purchase_requisition_multiple_vendor/__init__.py
odoo/addons/purchase_requisition_multiple_vendor/__manifest__.py
odoo/addons/purchase_requisition_multiple_vendor/i18n/it.po
odoo/addons/purchase_requisition_multiple_vendor/i18n/purchase_requisition_multiple_vendor.pot
odoo/addons/purchase_requisition_multiple_vendor/readme/CONTRIBUTORS.md
odoo/addons/purchase_requisition_multiple_vendor/readme/DESCRIPTION.md
odoo/addons/purchase_requisition_multiple_vendor/readme/USAGE.md
odoo/addons/purchase_requisition_multiple_vendor/static/description/icon.png
odoo/addons/purchase_requisition_multiple_vendor/static/description/index.html
odoo/addons/purchase_requisition_multiple_vendor/tests/__init__.py
odoo/addons/purchase_requisition_multiple_vendor/tests/test_purchase_requisition_multiple_vendors.py
odoo/addons/purchase_requisition_multiple_vendor/wizard/__init__.py
odoo/addons/purchase_requisition_multiple_vendor/wizard/purchase_requisition_create_alternative.py
odoo/addons/purchase_requisition_multiple_vendor/wizard/purchase_requisition_create_alternative.xml
odoo_addon_purchase_requisition_multiple_vendor-17.0.1.0.0.4.dist-info/METADATA
odoo_addon_purchase_requisition_multiple_vendor-17.0.1.0.0.4.dist-info/WHEEL
odoo_addon_purchase_requisition_multiple_vendor-17.0.1.0.0.4.dist-info/top_level.txt
odoo_addon_purchase_requisition_multiple_vendor-17.0.1.0.0.4.dist-info/RECORD
